dolphindb_tools/__init__.py
dolphindb_tools/dataloader/__init__.py
dolphindb_tools/dataloader/config.py
dolphindb_tools/dataloader/dataloader.py
dolphindb_tools/dataloader/datamanager.py
dolphindb_tools/dataloader/datasource.py
dolphindb_tools/dataloader/helper.py
dolphindb_tools/dataloader/utils.py
dolphindb_tools-0.2a1.dist-info/LICENSE
dolphindb_tools-0.2a1.dist-info/METADATA
dolphindb_tools-0.2a1.dist-info/WHEEL
dolphindb_tools-0.2a1.dist-info/top_level.txt
dolphindb_tools-0.2a1.dist-info/RECORD
