Metadata-Version: 2.1
Name: dolphindb-tools
Version: 0.2a1
Summary: A tool package based on DolphinDB Python API.
Home-page: https://www.dolphindb.com
Author: DolphinDB, Inc.
Author-email: support@dolphindb.com
Classifier: Development Status :: 2 - Pre-Alpha
Classifier: Programming Language :: Python
Classifier: Programming Language :: Python :: 3
Classifier: Operating System :: POSIX :: Linux
Classifier: Operating System :: Microsoft :: Windows
Classifier: Operating System :: MacOS
Classifier: Topic :: Software Development :: Libraries :: Python Modules
License-File: LICENSE
Requires-Dist: dolphindb >=1.30.19.4
Requires-Dist: intervaltree
Requires-Dist: numpy >=1.18.0
Requires-Dist: pandas >=1.0.0
Provides-Extra: pytorch
Requires-Dist: torch ; extra == 'pytorch'
Provides-Extra: tensorflow
Requires-Dist: tensorflow ; extra == 'tensorflow'
